searchxmlyandex/YandexXMLSearch.py
searchxmlyandex/__init__.py
searchxmlyandex-0.0.19.dist-info/LICENSE
searchxmlyandex-0.0.19.dist-info/METADATA
searchxmlyandex-0.0.19.dist-info/WHEEL
searchxmlyandex-0.0.19.dist-info/top_level.txt
searchxmlyandex-0.0.19.dist-info/RECORD
