Metadata-Version: 2.1
Name: searchxmlyandex
Version: 0.0.19
Summary: YandexXMLSearch API, XML to JSON converter
Home-page: https://github.com/0xSaiyajin/searchxmlyandex
Author: 0xSaiyajin
License: UNKNOWN
Platform: UNKNOWN
Classifier: Programming Language :: Python :: 3.6
Classifier: License :: OSI Approved :: MIT License
Classifier: Operating System :: OS Independent
Requires-Dist: requests
